sklearn_extender/__init__.py
sklearn_extender/coefficients.py
sklearn_extender/model_extender.py
sklearn_extender/prediction_intervals.py
sklearn_extender/timeseries_forecast.py
sklearn_extender/timeseries_splitter.py
sklearn_extender-0.0.5.dist-info/LICENSE.txt
sklearn_extender-0.0.5.dist-info/METADATA
sklearn_extender-0.0.5.dist-info/WHEEL
sklearn_extender-0.0.5.dist-info/top_level.txt
sklearn_extender-0.0.5.dist-info/RECORD
